reactor_di/__init__.py
reactor_di/caching.py
reactor_di/law_of_demeter.py
reactor_di/module.py
reactor_di/py.typed
reactor_di/type_utils.py
reactor_di-0.1.2.dist-info/METADATA
reactor_di-0.1.2.dist-info/WHEEL
reactor_di-0.1.2.dist-info/licenses/LICENSE
reactor_di-0.1.2.dist-info/RECORD
