Metadata-Version: 2.4
Name: reactor-di
Version: 0.1.2
Summary: A code generator for dependency injection (DI) in Python which is based on the mediator and factory patterns
Project-URL: Homepage, https://github.com/christian-schlichtherle/reactor-di-python
Project-URL: Issues, https://github.com/christian-schlichtherle/reactor-di-python/issues
Project-URL: Repository, https://github.com/christian-schlichtherle/reactor-di-python
Author: Christian Schlichtherle
License: MIT
License-File: LICENSE
Keywords: code-generation,dependency-injection,di,factory,mediator
Classifier: Development Status :: 4 - Beta
Classifier: Intended Audience :: Developers
Classifier: License :: OSI Approved :: MIT License
Classifier: Programming Language :: Python :: 3
Classifier: Programming Language :: Python :: 3.8
Classifier: Programming Language :: Python :: 3.9
Classifier: Programming Language :: Python :: 3.10
Classifier: Programming Language :: Python :: 3.11
Classifier: Programming Language :: Python :: 3.12
Classifier: Programming Language :: Python :: 3.13
Classifier: Topic :: Software Development :: Code Generators
Classifier: Topic :: Software Development :: Libraries :: Python Modules
Requires-Python: >=3.8
